pandas_selector/__init__.py
pandas_selector-1.5.0.dist-info/METADATA
pandas_selector-1.5.0.dist-info/WHEEL
pandas_selector-1.5.0.dist-info/RECORD
