Metadata-Version: 2.1
Name: pandas-selector
Version: 1.5.0
Summary: Stub package to install the matching pandas_paddles
Home-page: https://github.com/eikevons/pandas-paddles.git
License: MIT
Author: Eike von Seggern
Author-email: eikevons@mailbox.org
Requires-Python: >=3.7.0,<4.0.0
Classifier: Development Status :: 7 - Inactive
Classifier: License :: OSI Approved :: MIT License
Classifier: Programming Language :: Python :: 3
Classifier: Programming Language :: Python :: 3.7
Classifier: Programming Language :: Python :: 3.8
Classifier: Programming Language :: Python :: 3.9
Classifier: Programming Language :: Python :: 3.10
Classifier: Programming Language :: Python :: 3.11
Requires-Dist: pandas_paddles (==1.5.0)
Project-URL: Repository, https://github.com/eikevons/pandas-paddles.git
